[ 
	{ "_configuration":
		{ "_name" : "Boston" ,
		  "_field": [
			{ "_name": "_uuname[_uuname=_name]",
              "_data type": "_uuname[_uuname=\"_data type\"]>enumerator[_name=_string]",
              "_max capacity": "_uuname[_uuname=\"_max capacity\"]>enumerator[_name=\"_unique value\"]",
              "_descriptor type": "_uuname[_uuname=\"_descriptor type\"]>enumerator[_name=\"_by text\"]",
            },
            { "_name": "_uuname[_uuname=\"Registration Deadline\"]",
              "_data type": "_uuname[_uuname=\"_data type\"]>enumerator[_name=_datestamp]",
              "_max capacity": "_uuname[_uuname=\"_max capacity\"]>enumerator[_name=\"_unique value\"]"
            },
            { "_name": "_uuname[_uuname=\"Start Date\"]",
              "_data type": "_uuname[_uuname=\"_data type\"]>enumerator[_name=_datestamp]",
              "_max capacity": "_uuname[_uuname=\"_max capacity\"]>enumerator[_name=\"_unique value\"]"
            },
            { "_name": "_uuname[_uuname=\"End Date\"]",
              "_data type": "_uuname[_uuname=\"_data type\"]>enumerator[_name=_datestamp]",
              "_max capacity": "_uuname[_uuname=\"_max capacity\"]>enumerator[_name=\"_unique value\"]"
            },
            { "_name": "_uuname[_uuname=Inquiries]",
              "_data type": "_uuname[_uuname=\"_data type\"]>enumerator[_name=_object]",
              "_max capacity": "_uuname[_uuname=\"_max capacity\"]>enumerator[_name=\"_unique value\"]",
              "_object add rule": "_uuname[_uuname=\"_object add rule\"]>enumerator[_name=\"_create one\"]",
              "_of kind": "_uuname[_uuname=Inquiries]"
            },
            { "_name": "_uuname[_uuname=Enrollments]",
              "_data type": "_uuname[_uuname=\"_data type\"]>enumerator[_name=_object]",
              "_max capacity": "_uuname[_uuname=\"_max capacity\"]>enumerator[_name=\"_unique value\"]",
              "_object add rule": "_uuname[_uuname=\"_object add rule\"]>enumerator[_name=\"_create one\"]",
              "_of kind": "_uuname[_uuname=Enrollments]"
            },
            { "_name": "_uuname[_uuname=Experiences]",
              "_data type": "_uuname[_uuname=\"_data type\"]>enumerator[_name=_object]",
              "_max capacity": "_uuname[_uuname=\"_max capacity\"]>enumerator[_name=\"_unique value\"]",
              "_object add rule": "_uuname[_uuname=\"_object add rule\"]>enumerator[_name=\"_create one\"]",
              "_of kind": "_uuname[_uuname=Experiences]"
            }
          ]
      }
  }
]
